UACbypass/__init__.py
UACbypass/core.py
uac-1.0.2.dist-info/licenses/LICENSE
uac-1.0.2.dist-info/METADATA
uac-1.0.2.dist-info/WHEEL
uac-1.0.2.dist-info/top_level.txt
uac-1.0.2.dist-info/RECORD
