Metadata-Version: 2.4
Name: UAC
Version: 1.0.2
Summary: A python library that is an exploit for UAC Bypass on Windows. It works on any version of Windows and can execute a pyload(exe) with admin access without confirmation.
Author: Mohammad Taha Gorji
Author-email: MohammadTahaGorjiProfile@gmail.com
Classifier: Programming Language :: Python :: 3
Classifier: License :: OSI Approved :: MIT License
Classifier: Operating System :: OS Independent
Requires-Python: >=3.6
License-File: LICENSE
Dynamic: author
Dynamic: author-email
Dynamic: classifier
Dynamic: description
Dynamic: description-content-type
Dynamic: license-file
Dynamic: requires-python
Dynamic: summary
